MANIFEST.in
README.md
README.rst
setup.py
python_project/__init__.py
python_project/text.py
python_project.egg-info/PKG-INFO
python_project.egg-info/SOURCES.txt
python_project.egg-info/dependency_links.txt
python_project.egg-info/not-zip-safe
python_project.egg-info/requires.txt
python_project.egg-info/top_level.txt