Metadata-Version: 1.0
Name: python-project
Version: 0.21
Summary: Python Project Template
Home-page: http://github.com/rehmanz/python_project
Author: Zile Rehman
Author-email: rehmanz@yahoo.com
License: MIT
Platform: UNKNOWN
